[{"equipments":[],"clients":[],"work_nature":[],"_id":"5cd118392e5532c646b01222","name":"A K Hazra","org_name":"","email":"","address":"","city":"Kolkata","state":"West Bengal","office":""},{"equipments":[],"clients":[],"work_nature":[],"_id":"5cd118392e5532c646b01239","name":"Amlan Kumar Biswas","org_name":"","email":"","address":"","city":"Kolkata","state":"West Bengal","office":""},{"equipments":[],"clients":[],"work_nature":[],"_id":"5cd118392e5532c646b01231","name":"Ajit Singh","org_name":"","email":"","address":"","city":"Durgapur","state":"West Bengal","office":""},{"equipments":[],"clients":[],"work_nature":[],"_id":"5cd118392e5532c646b0123e","name":"Anup Mazumder","org_name":"","email":"","address":"","city":"Durgapur","state":"West Bengal","office":""},{"equipments":[],"clients":[],"work_nature":[],"_id":"5cd118392e5532c646b0123f","name":"Arindam Dey","org_name":"","email":"","address":"","city":"Durgapur","state":"West Bengal","office":""},{"equipments":[],"clients":[],"work_nature":[],"_id":"5cd118392e5532c646b01243","name":"Ashis Mondal","org_name":"","email":"","address":"","city":"Durgapur","state":"West Bengal","office":""},{"equipments":[],"clients":[],"work_nature":[],"_id":"5cd118392e5532c646b01249","name":"Ashoke Chandak","org_name":"","email":"","address":"","city":"Durgapur","state":"West Bengal","office":""},{"equipments":[],"clients":[],"work_nature":[],"_id":"5cd118392e5532c646b0124a","name":"Ashoke Kumar Samanta","org_name":"","email":"","address":"","city":"Kolkata","state":"West Bengal","office":""},{"equipments":[],"clients":[],"work_nature":[],"_id":"5cd118392e5532c646b01250","name":"Awadh Kishore Mishra","org_name":"M/S. Abhishek Construction Corporation","email":"accdgp@yahoo.com","address":"Rd-53 Saraswati Vihar Nabapally Benachity Durgapur Wb-713213","city":"Durgapur","state":"West Bengal","office":"919434172107"},{"equipments":[],"clients":[],"work_nature":[],"_id":"5cd118392e5532c646b01263","name":"Biswajit Bera","org_name":"","email":"","address":"","city":"Haldia","state":"West Bengal","office":""},{"equipments":[],"clients":[],"work_nature":[],"_id":"5cd118392e5532c646b01273","name":"Chandan Dey","org_name":"","email":"","address":"","city":"Durgapur","state":"West Bengal","office":""},{"equipments":[],"clients":[],"work_nature":[],"_id":"5cd118392e5532c646b01274","name":"Chandan Goswami","org_name":"","email":"","address":"","city":"Kolkata","state":"West Bengal","office":""},{"equipments":[],"clients":[],"work_nature":[],"_id":"5cd118392e5532c646b01299","name":"G.C. Gupta","org_name":"","email":"","address":"","city":"Kolkata","state":"West Bengal","office":""},{"equipments":[],"clients":[],"work_nature":[],"_id":"5cd118392e5532c646b0129d","name":"Ganesh Sen","org_name":"","email":"","address":"","city":"Durgapur","state":"West Bengal","office":""},{"equipments":[],"clients":[],"work_nature":[],"_id":"5cd118392e5532c646b012a3","name":"Girdhardas Bhatta","org_name":"","email":"","address":"","city":"Durgapur","state":"West Bengal","office":""},{"equipments":[],"clients":[],"work_nature":[],"_id":"5cd118392e5532c646b0136f","name":"Pradeep K Chowdhury","org_name":"M/S Primax Corporation","email":"chowdhury.pradeep@yahoo.com","address":"12-A Netaji Subhas Road Ground Floor-Rm-4 Kolkata-700001","city":"Kolkata","state":"West Bengal","office":"9433014997"},{"equipments":[],"clients":[],"work_nature":[],"_id":"5cd118392e5532c646b01374","name":"Pradip Kumar Mukherjee","org_name":"","email":"","address":"","city":"Kolkata","state":"West Bengal","office":""},{"equipments":[],"clients":[],"work_nature":[],"_id":"5cd118392e5532c646b0137d","name":"Probir Kumar Ghosh","org_name":"","email":"","address":"","city":"Kolkata","state":"West Bengal","office":""},{"equipments":[],"clients":[],"work_nature":[],"_id":"5cd118392e5532c646b01392","name":"R.C. Chouhan","org_name":"","email":"","address":"","city":"Durgapur","state":"West Bengal","office":""},{"equipments":[],"clients":[],"work_nature":[],"_id":"5cd118392e5532c646b013a7","name":"Rajib Manna","org_name":"","email":"","address":"","city":"Kolkata","state":"West Bengal","office":""},{"equipments":[],"clients":[],"work_nature":[],"_id":"5cd118392e5532c646b013b6","name":"Ranjit Kumar Debnath","org_name":"M/S. Tristar Painting & Engineering Co","email":"","address":"40 Durgachak New Market Durgachak (P.O) Haldia Dis Wb-721602","city":"Haldia","state":"West Bengal","office":"919564193595"},{"equipments":[],"clients":[],"work_nature":[],"_id":"5cd118392e5532c646b013eb","name":"Sanjay Dasgupta","org_name":"","email":"","address":"","city":"Kolkata","state":"West Bengal","office":""},{"equipments":[],"clients":[],"work_nature":[],"_id":"5cd118392e5532c646b013f9","name":"Shankar Chandra Dey","org_name":"","email":"","address":"","city":"Kolkata","state":"West Bengal","office":""},{"equipments":[],"clients":[],"work_nature":[],"_id":"5cd118392e5532c646b01409","name":"Subham Rudra","org_name":"","email":"","address":"","city":"Durgapur","state":"West Bengal","office":""},{"equipments":[],"clients":[],"work_nature":[],"_id":"5cd118392e5532c646b0140e","name":"Sudip Kumar Dutta","org_name":"M/S. Civcon Construction Pvt. Ltd","email":"covcpms@bsnl.in","address":"21a Shakespeare Sarani Kolkata 700017","city":"Kolkata","state":"West Bengal","office":"919830274895"},{"equipments":[],"clients":[],"work_nature":[],"_id":"5cd118392e5532c646b01410","name":"Sujoy Kumar Nag","org_name":"","email":"","address":"","city":"Kolkata","state":"West Bengal","office":""},{"equipments":[],"clients":[],"work_nature":[],"_id":"5cd118392e5532c646b01411","name":"Sumanta Ghosh","org_name":"","email":"","address":"","city":"Kolkata","state":"West Bengal","office":""},{"equipments":[],"clients":[],"work_nature":[],"_id":"5cd118392e5532c646b0141b","name":"Sushanta Kumar Basu","org_name":"M/S. Centex (India) Engineers (P) Ltd","email":"sushantabasu28@gmail.com","address":"3rd Fl / 21 Old Court House Stree Kolkata","city":"Kolkata","state":"West Bengal","office":"(033) 22131533 / 983"},{"equipments":[],"clients":[],"work_nature":[],"_id":"5cd118392e5532c646b0141c","name":"Sushil Kumar Ghosh","org_name":"","email":"","address":"","city":"Kolkata","state":"West Bengal","office":""},{"equipments":[],"clients":[],"work_nature":[],"_id":"5cd118392e5532c646b0141e","name":"Swapan Sen","org_name":"","email":"","address":"","city":"Durgapur","state":"West Bengal","office":""}]